muxtools_styx/__init__.py
muxtools_styx/__main__.py
muxtools_styx/py.typed
muxtools_styx/internals/__init__.py
muxtools_styx/internals/muxing.py
muxtools_styx/internals/tagfixing.py
muxtools_styx-0.2.0.dist-info/LICENSE
muxtools_styx-0.2.0.dist-info/METADATA
muxtools_styx-0.2.0.dist-info/WHEEL
muxtools_styx-0.2.0.dist-info/entry_points.txt
muxtools_styx-0.2.0.dist-info/top_level.txt
muxtools_styx-0.2.0.dist-info/RECORD
