Metadata-Version: 2.2
Name: muxtools-styx
Version: 0.2.0
Summary: Commandline Tool for the Styx backend/downloader using muxtools
Author-email: Vodes <vodes.imp@gmail.com>
License: MPL 2.0
Project-URL: Source Code, https://github.com/Vodes/muxtools-styx
Classifier: Natural Language :: English
Classifier: Intended Audience :: Developers
Classifier: Programming Language :: Python :: 3.10
Classifier: Operating System :: OS Independent
Classifier: Typing :: Typed
Classifier: Topic :: Multimedia :: Sound/Audio
Classifier: Topic :: Multimedia :: Sound/Audio :: Conversion
Classifier: Topic :: Multimedia :: Video
Classifier: Topic :: Multimedia :: Video :: Conversion
Classifier: License :: OSI Approved :: Mozilla Public License 2.0 (MPL 2.0)
Requires-Python: >=3.10
License-File: LICENSE
Requires-Dist: muxtools>=0.2.1
